mobsf/DynamicAnalyzer/__init__.py
mobsf/DynamicAnalyzer/admin.py
mobsf/DynamicAnalyzer/forms.py
mobsf/DynamicAnalyzer/models.py
mobsf/DynamicAnalyzer/tests.py
mobsf/DynamicAnalyzer/tools/__init__.py
mobsf/DynamicAnalyzer/tools/apk_patcher.py
mobsf/DynamicAnalyzer/tools/frida_scripts/android/auxiliary/class_trace.js
mobsf/DynamicAnalyzer/tools/frida_scripts/android/auxiliary/get_loaded_classes.js
mobsf/DynamicAnalyzer/tools/frida_scripts/android/auxiliary/get_methods.js
mobsf/DynamicAnalyzer/tools/frida_scripts/android/auxiliary/search_class_pattern.js
mobsf/DynamicAnalyzer/tools/frida_scripts/android/auxiliary/string_catch.js
mobsf/DynamicAnalyzer/tools/frida_scripts/android/auxiliary/string_compare.js
mobsf/DynamicAnalyzer/tools/frida_scripts/android/default/api_monitor.js
mobsf/DynamicAnalyzer/tools/frida_scripts/android/default/debugger_check_bypass.js
mobsf/DynamicAnalyzer/tools/frida_scripts/android/default/dump_clipboard.js
mobsf/DynamicAnalyzer/tools/frida_scripts/android/default/root_bypass.js
mobsf/DynamicAnalyzer/tools/frida_scripts/android/default/ssl_pinning_bypass.js
mobsf/DynamicAnalyzer/tools/frida_scripts/android/others/app-environment.js
mobsf/DynamicAnalyzer/tools/frida_scripts/android/others/audit-webview.js
mobsf/DynamicAnalyzer/tools/frida_scripts/android/others/bypass-adb-detection.js
mobsf/DynamicAnalyzer/tools/frida_scripts/android/others/bypass-emulator-detection.js
mobsf/DynamicAnalyzer/tools/frida_scripts/android/others/bypass-react-native-emulator-detection.js
mobsf/DynamicAnalyzer/tools/frida_scripts/android/others/crypto-aes-key.js
mobsf/DynamicAnalyzer/tools/frida_scripts/android/others/crypto-dump-keystore.js
mobsf/DynamicAnalyzer/tools/frida_scripts/android/others/crypto-keyguard-credential-intent.js
mobsf/DynamicAnalyzer/tools/frida_scripts/android/others/crypto-trace-cipher.js
mobsf/DynamicAnalyzer/tools/frida_scripts/android/others/crypto-trace-keygenparameterspec.js
mobsf-4.4.5.dist-info/LICENSE
mobsf-4.4.5.dist-info/LICENSES/AdminLTE_theme.txt
mobsf-4.4.5.dist-info/LICENSES/AntiEmulator.txt
mobsf-4.4.5.dist-info/LICENSES/FSecureLabs_frida_scripts.txt
mobsf-4.4.5.dist-info/LICENSES/IP2LOCATION LITE DATA.txt
mobsf-4.4.5.dist-info/LICENSES/Rootcloak.txt
mobsf-4.4.5.dist-info/LICENSES/ac-pm_tools.txt
mobsf-4.4.5.dist-info/LICENSES/androguard.txt
mobsf-4.4.5.dist-info/LICENSES/apkinspector.txt
mobsf-4.4.5.dist-info/LICENSES/apksigner.txt
mobsf-4.4.5.dist-info/LICENSES/backsmali.txt
mobsf-4.4.5.dist-info/LICENSES/class-dump-z.txt
mobsf-4.4.5.dist-info/LICENSES/droidmon.txt
mobsf-4.4.5.dist-info/LICENSES/exodus-core.txt
mobsf-4.4.5.dist-info/LICENSES/frida.txt
mobsf-4.4.5.dist-info/LICENSES/ios_binary_analysis_rules.txt
mobsf-4.4.5.dist-info/LICENSES/jadx.txt
mobsf-4.4.5.dist-info/LICENSES/maltrail_blacklist.txt
mobsf-4.4.5.dist-info/LICENSES/vd2svg.txt
mobsf-4.4.5.dist-info/METADATA
mobsf-4.4.5.dist-info/WHEEL
mobsf-4.4.5.dist-info/entry_points.txt
mobsf-4.4.5.dist-info/RECORD
