Metadata-Version: 2.1
Name: mobsf
Version: 4.4.5
Summary: Mobile Security Framework (MobSF) is an automated, all-in-one mobile application (Android/iOS/Windows) pen-testing, malware analysis and security assessment framework capable of performing static and dynamic analysis.
Home-page: https://github.com/MobSF/Mobile-Security-Framework-MobSF
License: GPL-3.0-only
Keywords: mobsf,mobile security framework,mobile security,security tool,static analysis,dynamic analysis,malware analysis
Author: Ajin Abraham
Author-email: ajin@opensecurity.in
Requires-Python: >=3.12,<4.0
Classifier: Development Status :: 5 - Production/Stable
Classifier: Intended Audience :: Developers
Classifier: License :: OSI Approved :: GNU General Public License v3 (GPLv3)
Classifier: Programming Language :: Python :: 3
Classifier: Programming Language :: Python :: 3.12
Classifier: Programming Language :: Python :: 3.13
Classifier: Topic :: Security
Classifier: Topic :: Software Development :: Quality Assurance
Requires-Dist: apkid (>=3.0.0,<4.0.0)
Requires-Dist: apksigtool (>=0.1.0,<0.2.0)
Requires-Dist: arpy (>=2.3.0)
Requires-Dist: asn1crypto (>=1.4.0)
Requires-Dist: bcrypt (==4.0.1)
Requires-Dist: bleach (>=6.2.0,<7.0.0)
Requires-Dist: bs4 (>=0.0.1)
Requires-Dist: colorlog (>=4.7.2)
Requires-Dist: defusedxml (>=0.7.1,<0.8.0)
Requires-Dist: distro (>=1.5.0)
Requires-Dist: django (>=3.1.5)
Requires-Dist: django-q2 (>=1.7.4,<2.0.0)
Requires-Dist: django-ratelimit (>=4.1.0,<5.0.0)
Requires-Dist: frida (>=17.0.0)
Requires-Dist: frida-tools (>=14.3.0,<15.0.0)
Requires-Dist: google-play-scraper (>=0.1.2)
Requires-Dist: gunicorn (>=20.0.4) ; sys_platform != "win32"
Requires-Dist: http-tools (>=6.0.0)
Requires-Dist: ip2location (>=8.10.4,<9.0.0)
Requires-Dist: libsast (>=3.1.6,<4.0.0)
Requires-Dist: lief (>=0.16.6,<0.17.0)
Requires-Dist: macholib (>=1.14)
Requires-Dist: openstep-parser (>=2.0.1)
Requires-Dist: packaging (>=24.2)
Requires-Dist: paramiko (>=3.3.1,<4.0.0)
Requires-Dist: pdfkit (>=0.6.1)
Requires-Dist: psutil (>=5.8.0)
Requires-Dist: psycopg2-binary (>=2.9.10,<3.0.0)
Requires-Dist: python3-saml (>=1.16.0,<2.0.0)
Requires-Dist: requests (>=2.25.1)
Requires-Dist: rsa (>=4.7)
Requires-Dist: shelljob (>=0.6.2)
Requires-Dist: six (>=1.16.0)
Requires-Dist: svgutils (>=0.3.4)
Requires-Dist: tldextract (>=5.1.3)
Requires-Dist: tzdata (>=2023.3,<2024.0)
Requires-Dist: waitress (>=3.0.1) ; sys_platform == "win32"
Requires-Dist: whitenoise (>=6.8.2)
Project-URL: Bug Tracker, https://github.com/MobSF/Mobile-Security-Framework-MobSF/issues
Project-URL: Documentation, https://mobsf.github.io/docs/
Project-URL: Repository, https://github.com/MobSF/Mobile-Security-Framework-MobSF
